oh_gsf/__init__.py
oh_gsf/binaryStream.py
oh_gsf/encoding7Bit.py
oh_gsf/streamEncoder.py
openHistorian/__init__.py
openHistorian/deviceRecord.py
openHistorian/historianConnection.py
openHistorian/historianInstance.py
openHistorian/historianKey.py
openHistorian/historianKeyValueEncoder.py
openHistorian/historianValue.py
openHistorian/measurementRecord.py
openHistorian/metadataCache.py
openHistorian/phasorRecord.py
openhistorian-1.0.7.dist-info/licenses/LICENSE
snapDB/__init__.py
snapDB/databaseInfo.py
snapDB/encodingDefinition.py
snapDB/enumerations.py
snapDB/fixedSizeKeyValueEncoder.py
snapDB/keyValueEncoderBase.py
snapDB/library.py
snapDB/matchFilterBase.py
snapDB/pointIDMatchFilter.py
snapDB/pointReader.py
snapDB/readerOptions.py
snapDB/seekFilterBase.py
snapDB/snapClientDatabase.py
snapDB/snapConnection.py
snapDB/snapTypeBase.py
snapDB/timestampSeekFilter.py
snapDB/treeStream.py
openhistorian-1.0.7.dist-info/METADATA
openhistorian-1.0.7.dist-info/WHEEL
openhistorian-1.0.7.dist-info/top_level.txt
openhistorian-1.0.7.dist-info/RECORD
