Metadata-Version: 2.4
Name: openhistorian
Version: 1.0.7
Summary: openHistorian Python API
Home-page: https://github.com/GridProtectionAlliance/openhistorian-python
Download-URL: https://pypi.org/project/openhistorian/
Author: J. Ritchie Carroll
Author-email: rcarroll@gridprotectionalliance.org
Project-URL: Bug Tracker, https://github.com/GridProtectionAlliance/openhistorian-python/issues
Project-URL: Documentation, https://gridprotectionalliance.github.io/openhistorian-python/
Project-URL: Source Code, https://github.com/GridProtectionAlliance/openhistorian-python
Keywords: openHistorian,streaming,key-value,time-series,database,synchrophasor
Classifier: Development Status :: 5 - Production/Stable
Classifier: Intended Audience :: Science/Research
Classifier: Intended Audience :: Developers
Classifier: Topic :: Database :: Front-Ends
Classifier: Programming Language :: Python :: 3.9
Classifier: License :: OSI Approved :: MIT License
Classifier: Operating System :: OS Independent
Requires-Python: >=3.9
License-File: LICENSE
Dynamic: download-url
Dynamic: license-file
